pyvo/__init__.py
pyvo/_astropy_init.py
pyvo/samp.py
pyvo/version.py
pyvo/auth/__init__.py
pyvo/auth/authsession.py
pyvo/auth/authurls.py
pyvo/auth/credentialstore.py
pyvo/auth/securitymethods.py
pyvo/auth/tests/__init__.py
pyvo/auth/tests/conftest.py
pyvo/auth/tests/test_auth.py
pyvo/auth/tests/data/tap/capabilities.xml
pyvo/dal/__init__.py
pyvo/dal/adhoc.py
pyvo/dal/dbapi2.py
pyvo/dal/exceptions.py
pyvo/dal/mimetype.py
pyvo/dal/params.py
pyvo/dal/query.py
pyvo/dal/scs.py
pyvo/dal/sia.py
pyvo/dal/sia2.py
pyvo/dal/sla.py
pyvo/dal/ssa.py
pyvo/dal/tap.py
pyvo/dal/vosi.py
pyvo/dal/tests/__init__.py
pyvo/dal/tests/conftest.py
pyvo/dal/tests/make_testdata.py
pyvo/dal/tests/test_adhoc.py
pyvo/dal/tests/test_datalink.py
pyvo/dal/tests/test_mimetype.py
pyvo/dal/tests/test_monkeypatch.py
pyvo/dal/tests/test_params.py
pyvo/dal/tests/test_query.py
pyvo/dal/tests/test_scs.py
pyvo/dal/tests/test_sia.py
pyvo/dal/tests/test_sia2.py
pyvo/dal/tests/test_sia2_remote.py
pyvo/dal/tests/test_sla.py
pyvo/dal/tests/test_ssa.py
pyvo/dal/tests/test_tap.py
pyvo/dal/tests/data/monkeypatch.xml
pyvo/dal/tests/data/datalink/cutout1.xml
pyvo/dal/tests/data/datalink/cutout2.xml
pyvo/dal/tests/data/datalink/datalink-obscore.xml
pyvo/dal/tests/data/datalink/datalink-ssa.xml
pyvo/dal/tests/data/datalink/datalink.desise
pyvo/dal/tests/data/datalink/datalink.xml
pyvo/dal/tests/data/datalink/proc.xml
pyvo/dal/tests/data/datalink/proc_inf.xml
pyvo/dal/tests/data/datalink/proc_units.xml
pyvo/dal/tests/data/mimetype/ivoa_logo.jpg
pyvo/dal/tests/data/mimetype/test.fits
pyvo/dal/tests/data/query/basic.xml
pyvo/dal/tests/data/query/dataset.xml
pyvo/dal/tests/data/query/errorstatus.xml
pyvo/dal/tests/data/query/firstresource.xml
pyvo/dal/tests/data/query/missingcolumns.xml
pyvo/dal/tests/data/query/missingresource.xml
pyvo/dal/tests/data/query/missingtable.xml
pyvo/dal/tests/data/query/overflowstatus.xml
pyvo/dal/tests/data/query/rootinfo.xml
pyvo/dal/tests/data/query/tableinfo.xml
pyvo-1.6.dist-info/LICENSE.rst
pyvo-1.6.dist-info/METADATA
pyvo-1.6.dist-info/WHEEL
pyvo-1.6.dist-info/top_level.txt
pyvo-1.6.dist-info/RECORD
