Metadata-Version: 2.1
Name: pyvo
Version: 1.6
Summary: Astropy affiliated package for accessing Virtual Observatory data and services
Author: the PyVO Developers
License: BSD
Project-URL: Source, https://github.com/astropy/pyvo
Project-URL: Documentation, https:/pyvo.readthedocs.io
Classifier: Intended Audience :: Science/Research
Classifier: License :: OSI Approved :: BSD License
Classifier: Operating System :: OS Independent
Classifier: Programming Language :: Python
Classifier: Programming Language :: Python :: 3
Classifier: Topic :: Database
Classifier: Topic :: Scientific/Engineering :: Astronomy
Classifier: Topic :: Software Development :: Libraries
Classifier: License :: OSI Approved :: BSD License
Requires-Python: >=3.8
License-File: LICENSE.rst
Requires-Dist: astropy>=4.1
Requires-Dist: requests
Provides-Extra: all
Requires-Dist: pillow; extra == "all"
Requires-Dist: defusedxml; extra == "all"
Provides-Extra: test
Requires-Dist: pytest-doctestplus>=0.13; extra == "test"
Requires-Dist: pytest-astropy; extra == "test"
Requires-Dist: requests-mock; extra == "test"
Provides-Extra: docs
Requires-Dist: sphinx-astropy; extra == "docs"
